pip_services4_elasticsearch/__init__.py
pip_services4_elasticsearch/build/DefaultElasticSearchFactory.py
pip_services4_elasticsearch/build/__init__.py
pip_services4_elasticsearch/log/ElasticSearchLogger.py
pip_services4_elasticsearch/log/__init__.py
pip_services4_elasticsearch-3.1.6.dist-info/LICENSE
pip_services4_elasticsearch-3.1.6.dist-info/METADATA
pip_services4_elasticsearch-3.1.6.dist-info/WHEEL
pip_services4_elasticsearch-3.1.6.dist-info/top_level.txt
pip_services4_elasticsearch-3.1.6.dist-info/zip-safe
pip_services4_elasticsearch-3.1.6.dist-info/RECORD
